conterm/__init__.py
conterm/__main__.py
conterm/logging.py
conterm/cli/__init__.py
conterm/cli/select.py
conterm/cli/task.py
conterm/cli/util.py
conterm/control/__init__.py
conterm/control/actions.py
conterm/control/event.py
conterm/control/keys.py
conterm/control/unix.py
conterm/control/win.py
conterm/examples/controls.py
conterm/examples/logging.py
conterm/examples/markup.py
conterm/examples/pprint.py
conterm/examples/preview.py
conterm/examples/cli/full.py
conterm/examples/cli/select.py
conterm/examples/cli/tasks.py
conterm/pretty/__init__.py
conterm/pretty/pprint.py
conterm/pretty/themes.py
conterm/pretty/markup/__init__.py
conterm/pretty/markup/color.py
conterm/pretty/markup/color_consts.py
conterm/pretty/markup/macro.py
conterm/pretty/markup/preview.py
conterm/pretty/markup/util.py
conterm-0.1.0.dist-info/METADATA
conterm-0.1.0.dist-info/WHEEL
conterm-0.1.0.dist-info/entry_points.txt
conterm-0.1.0.dist-info/licenses/LICENSE
conterm-0.1.0.dist-info/RECORD
