Metadata-Version: 2.1
Name: conterm
Version: 0.1.0
Summary: Simple library built around making terminal interaction easy.
Project-URL: Github, https://github.com/Tired-Fox/conterm
Author-email: Tired Fox <zboehm104@gmail.com>
License-Expression: MIT
License-File: LICENSE
Classifier: License :: OSI Approved :: MIT License
Classifier: Operating System :: OS Independent
Classifier: Programming Language :: Python :: 3
Requires-Python: >=3.9
Provides-Extra: click
Requires-Dist: click; extra == 'click'
Provides-Extra: dev
Requires-Dist: black; extra == 'dev'
Requires-Dist: requests; extra == 'dev'
Requires-Dist: ruff; extra == 'dev'
Provides-Extra: tests
Requires-Dist: pytest; extra == 'tests'
Requires-Dist: pytest-cov; extra == 'tests'
